glse/__init__.py
glse/_version.py
glse/cli.py
glse/custom.css
glse/figure_tab.py
glse/figures/arrow.py
glse/figures/contour.py
glse/figures/curve.py
glse/figures/figure.py
glse/figures/fits.py
glse/figures/heatmap.py
glse/figures/histogram.py
glse/figures/hlines and vlines.py
glse/figures/line.py
glse/figures/point.py
glse/figures/polygon.py
glse/figures/scatter.py
glse/figures/stream.py
glse/figures/table.py
glse/figures/text.py
glse/figures/vectorfield.py
glse/fits_tab.py
glse/glse.py
glse/other_gl_tab.py
glse/plotting_1d_tab.py
glse/plotting_2d_tab.py
glse/shapes_tab.py
glse/widgets.py
glse-1.0.1.dist-info/LICENSE
glse-1.0.1.dist-info/METADATA
glse-1.0.1.dist-info/WHEEL
glse-1.0.1.dist-info/entry_points.txt
glse-1.0.1.dist-info/RECORD
