Metadata-Version: 2.1
Name: glse
Version: 1.0.1
Summary: A GUI editor for GraphingLib style files
License: MIT
Author: Gustave Coulombe
Author-email: magikgus@gmail.com
Requires-Python: >=3.10,<3.13
Classifier: License :: OSI Approved :: MIT License
Classifier: Programming Language :: Python :: 3
Classifier: Programming Language :: Python :: 3.10
Classifier: Programming Language :: Python :: 3.11
Classifier: Programming Language :: Python :: 3.12
Requires-Dist: graphinglib (>=1.5.0,<1.6.0)
Requires-Dist: pyside6 (>=6.7.1,<7.0.0)
Requires-Dist: qt-material (>=2.14,<3.0)
Requires-Dist: requests (>=2.31.0,<3.0.0)
Requires-Dist: setuptools-scm (>=8.0.4,<9.0.0)
